var asm = Packages.org.objectweb.asm;

var ASM4 = 4 << 16 | 0 << 8 | 0;

var V1_1 = 3 << 16 | 45;
var V1_2 = 0 << 16 | 46;
var V1_3 = 0 << 16 | 47;
var V1_4 = 0 << 16 | 48;
var V1_5 = 0 << 16 | 49;
var V1_6 = 0 << 16 | 50;
var V1_7 = 0 << 16 | 51;

var ACC_PUBLIC = 0x0001;
var ACC_PRIVATE = 0x0002;
var ACC_PROTECTED = 0x0004;
var ACC_STATIC = 0x0008;
var ACC_FINAL = 0x0010;
var ACC_SUPER = 0x0020;
var ACC_SYNCHRONIZED = 0x0020;
var ACC_VOLATILE = 0x0040;
var ACC_BRIDGE = 0x0040;
var ACC_VARARGS = 0x0080;
var ACC_TRANSIENT = 0x0080;
var ACC_NATIVE = 0x0100;
var ACC_INTERFACE = 0x0200;
var ACC_ABSTRACT = 0x0400;
var ACC_STRICT = 0x0800;
var ACC_SYNTHETIC = 0x1000;
var ACC_ANNOTATION = 0x2000;
var ACC_ENUM = 0x4000;
var ACC_DEPRECATED = 0x20000;

var T_BOOLEAN = 4;
var T_CHAR = 5;
var T_FLOAT = 6;
var T_DOUBLE = 7;
var T_BYTE = 8;
var T_SHORT = 9;
var T_var = 10;
var T_LONG = 11;

var H_GETFIELD = 1;
var H_GETSTATIC = 2;
var H_PUTFIELD = 3;
var H_PUTSTATIC = 4;
var H_INVOKEVIRTUAL = 5;
var H_INVOKESTATIC = 6;
var H_INVOKESPECIAL = 7;
var H_NEWINVOKESPECIAL = 8;
var H_INVOKEINTERFACE = 9;

var F_NEW = -1;
var F_FULL = 0;
var F_APPEND = 1;
var F_CHOP = 2;
var F_SAME = 3;
var F_SAME1 = 4;

var TOP = asm.Opcodes.TOP;
var INTEGER = asm.Opcodes.INTEGER;
var FLOAT = asm.Opcodes.FLOAT;
var DOUBLE = asm.Opcodes.DOUBLE;
var LONG = asm.Opcodes.LONG;
var NULL = asm.Opcodes.NULL;
var UNINITIALIZED_THIS = asm.Opcodes.UNINITIALIZED_THIS;

var NOP = 0;
var ACONST_NULL = 1;
var ICONST_M1 = 2;
var ICONST_0 = 3;
var ICONST_1 = 4;
var ICONST_2 = 5;
var ICONST_3 = 6;
var ICONST_4 = 7;
var ICONST_5 = 8;
var LCONST_0 = 9;
var LCONST_1 = 10;
var FCONST_0 = 11;
var FCONST_1 = 12;
var FCONST_2 = 13;
var DCONST_0 = 14;
var DCONST_1 = 15;
var BIPUSH = 16;
var SIPUSH = 17;
var LDC = 18;
var ILOAD = 21;
var LLOAD = 22;
var FLOAD = 23;
var DLOAD = 24;
var ALOAD = 25;
var IALOAD = 46;
var LALOAD = 47;
var FALOAD = 48;
var DALOAD = 49;
var AALOAD = 50;
var BALOAD = 51;
var CALOAD = 52;
var SALOAD = 53;
var ISTORE = 54;
var LSTORE = 55;
var FSTORE = 56;
var DSTORE = 57;
var ASTORE = 58;
var IASTORE = 79;
var LASTORE = 80;
var FASTORE = 81;
var DASTORE = 82;
var AASTORE = 83;
var BASTORE = 84;
var CASTORE = 85;
var SASTORE = 86;
var POP = 87;
var POP2 = 88;
var DUP = 89;
var DUP_X1 = 90;
var DUP_X2 = 91;
var DUP2 = 92;
var DUP2_X1 = 93;
var DUP2_X2 = 94;
var SWAP = 95;
var IADD = 96;
var LADD = 97;
var FADD = 98;
var DADD = 99;
var ISUB = 100;
var LSUB = 101;
var FSUB = 102;
var DSUB = 103;
var IMUL = 104;
var LMUL = 105;
var FMUL = 106;
var DMUL = 107;
var IDIV = 108;
var LDIV = 109;
var FDIV = 110;
var DDIV = 111;
var IREM = 112;
var LREM = 113;
var FREM = 114;
var DREM = 115;
var INEG = 116;
var LNEG = 117;
var FNEG = 118;
var DNEG = 119;
var ISHL = 120;
var LSHL = 121;
var ISHR = 122;
var LSHR = 123;
var IUSHR = 124;
var LUSHR = 125;
var IAND = 126;
var LAND = 127;
var IOR = 128;
var LOR = 129;
var IXOR = 130;
var LXOR = 131;
var IINC = 132;
var I2L = 133;
var I2F = 134;
var I2D = 135;
var L2I = 136;
var L2F = 137;
var L2D = 138;
var F2I = 139;
var F2L = 140;
var F2D = 141;
var D2I = 142;
var D2L = 143;
var D2F = 144;
var I2B = 145;
var I2C = 146;
var I2S = 147;
var LCMP = 148;
var FCMPL = 149;
var FCMPG = 150;
var DCMPL = 151;
var DCMPG = 152;
var IFEQ = 153;
var IFNE = 154;
var IFLT = 155;
var IFGE = 156;
var IFGT = 157;
var IFLE = 158;
var IF_ICMPEQ = 159;
var IF_ICMPNE = 160;
var IF_ICMPLT = 161;
var IF_ICMPGE = 162;
var IF_ICMPGT = 163;
var IF_ICMPLE = 164;
var IF_ACMPEQ = 165;
var IF_ACMPNE = 166;
var GOTO = 167;
var JSR = 168;
var RET = 169;
var TABLESWITCH = 170;
var LOOKUPSWITCH = 171;
var IRETURN = 172;
var LRETURN = 173;
var FRETURN = 174;
var DRETURN = 175;
var ARETURN = 176;
var RETURN = 177;
var GETSTATIC = 178;
var PUTSTATIC = 179;
var GETFIELD = 180;
var PUTFIELD = 181;
var INVOKEVIRTUAL = 182;
var INVOKESPECIAL = 183;
var INVOKESTATIC = 184;
var INVOKEINTERFACE = 185;
var INVOKEDYNAMIC = 186;
var NEW = 187;
var NEWARRAY = 188;
var ANEWARRAY = 189;
var ARRAYLENGTH = 190;
var ATHROW = 191;
var CHECKCAST = 192;
var INSTANCEOF = 193;
var MONITORENTER = 194;
var MONITOREXIT = 195;
var MULTIANEWARRAY = 197;
var IFNULL = 198;
var IFNONNULL = 199;
